{
  "test_name": "forward_model_bunching_validation",
  "n_galaxies": 113,
  "n_bec_preferred": 38,
  "n_nfw_preferred": 60,
  "n_indistinguishable": 15,
  "mean_daic": -20.301,
  "median_daic": -4.11,
  "sum_daic": -2294.0,
  "wilcoxon_p": 0.000727,
  "spearman_logMs": {
    "rho": -0.0518,
    "p": 0.5857
  },
  "spearman_Xmed": {
    "rho": -0.1454,
    "p": 0.1243
  },
  "mass_trend": "INCONCLUSIVE \u2014 no significant mass trend",
  "overall_verdict": "NFW-FAVORED",
  "comparison_test8_pipeline": "\u0394AIC = +9.7",
  "comparison_test8_sparc": "\u0394AIC = -40",
  "per_galaxy": [
    {
      "name": "UGC03580",
      "logMs": 9.82,
      "xi_kpc": 2.78,
      "N_pts": 47,
      "X_min": 0.04,
      "X_med": 0.99,
      "X_max": 9.75,
      "chi2_nfw": 451.92,
      "chi2_bec": 335.34,
      "rchi2_nfw": 10.043,
      "rchi2_bec": 7.452,
      "daic": 116.58,
      "nfw_log_rhos": 4.87,
      "nfw_log_rs": 2.5,
      "bec_log_rhoc": 6.77,
      "bec_log_rc": 1.04
    },
    {
      "name": "ESO563-G021",
      "logMs": 11.19,
      "xi_kpc": 13.44,
      "N_pts": 30,
      "X_min": 0.033,
      "X_med": 1.32,
      "X_max": 3.15,
      "chi2_nfw": 228.04,
      "chi2_bec": 133.66,
      "rchi2_nfw": 8.144,
      "rchi2_bec": 4.774,
      "daic": 94.37,
      "nfw_log_rhos": 5.96,
      "nfw_log_rs": 2.1,
      "bec_log_rhoc": 7.52,
      "bec_log_rc": 1.06
    },
    {
      "name": "F571-8",
      "logMs": 9.71,
      "xi_kpc": 2.43,
      "N_pts": 13,
      "X_min": 0.091,
      "X_med": 1.96,
      "X_max": 6.4,
      "chi2_nfw": 136.62,
      "chi2_bec": 70.68,
      "rchi2_nfw": 12.42,
      "rchi2_bec": 6.426,
      "daic": 65.94,
      "nfw_log_rhos": 5.2,
      "nfw_log_rs": 2.5,
      "bec_log_rhoc": 7.23,
      "bec_log_rc": 0.89
    },
    {
      "name": "UGC02916",
      "logMs": 10.79,
      "xi_kpc": 8.49,
      "N_pts": 43,
      "X_min": 0.044,
      "X_med": 0.87,
      "X_max": 4.48,
      "chi2_nfw": 126.75,
      "chi2_bec": 78.48,
      "rchi2_nfw": 3.091,
      "rchi2_bec": 1.914,
      "daic": 48.27,
      "nfw_log_rhos": 6.16,
      "nfw_log_rs": 1.6,
      "bec_log_rhoc": 7.08,
      "bec_log_rc": 1.02
    },
    {
      "name": "UGC09037",
      "logMs": 10.54,
      "xi_kpc": 6.31,
      "N_pts": 22,
      "X_min": 0.385,
      "X_med": 2.4,
      "X_max": 4.43,
      "chi2_nfw": 103.09,
      "chi2_bec": 64.54,
      "rchi2_nfw": 5.155,
      "rchi2_bec": 3.227,
      "daic": 38.55,
      "nfw_log_rhos": 4.83,
      "nfw_log_rs": 2.5,
      "bec_log_rhoc": 6.5,
      "bec_log_rc": 1.21
    },
    {
      "name": "NGC2903",
      "logMs": 10.61,
      "xi_kpc": 6.9,
      "N_pts": 34,
      "X_min": 0.046,
      "X_med": 1.32,
      "X_max": 3.62,
      "chi2_nfw": 297.27,
      "chi2_bec": 266.9,
      "rchi2_nfw": 9.29,
      "rchi2_bec": 8.341,
      "daic": 30.37,
      "nfw_log_rhos": 6.28,
      "nfw_log_rs": 1.6,
      "bec_log_rhoc": 7.25,
      "bec_log_rc": 0.94
    },
    {
      "name": "NGC3877",
      "logMs": 10.56,
      "xi_kpc": 6.49,
      "N_pts": 13,
      "X_min": 0.134,
      "X_med": 0.94,
      "X_max": 1.75,
      "chi2_nfw": 52.91,
      "chi2_bec": 30.41,
      "rchi2_nfw": 4.81,
      "rchi2_bec": 2.765,
      "daic": 22.49,
      "nfw_log_rhos": 7.07,
      "nfw_log_rs": 0.96,
      "bec_log_rhoc": 7.85,
      "bec_log_rc": 0.46
    },
    {
      "name": "ESO079-G014",
      "logMs": 10.41,
      "xi_kpc": 5.48,
      "N_pts": 15,
      "X_min": 0.075,
      "X_med": 1.16,
      "X_max": 3.04,
      "chi2_nfw": 28.3,
      "chi2_bec": 5.87,
      "rchi2_nfw": 2.177,
      "rchi2_bec": 0.452,
      "daic": 22.43,
      "nfw_log_rhos": 5.26,
      "nfw_log_rs": 2.5,
      "bec_log_rhoc": 7.31,
      "bec_log_rc": 0.87
    },
    {
      "name": "NGC3917",
      "logMs": 10.04,
      "xi_kpc": 3.57,
      "N_pts": 17,
      "X_min": 0.244,
      "X_med": 2.2,
      "X_max": 4.16,
      "chi2_nfw": 36.76,
      "chi2_bec": 14.64,
      "rchi2_nfw": 2.451,
      "rchi2_bec": 0.976,
      "daic": 22.12,
      "nfw_log_rhos": 6.28,
      "nfw_log_rs": 1.52,
      "bec_log_rhoc": 7.46,
      "bec_log_rc": 0.7
    },
    {
      "name": "NGC2976",
      "logMs": 9.23,
      "xi_kpc": 1.4,
      "N_pts": 27,
      "X_min": 0.079,
      "X_med": 0.72,
      "X_max": 1.62,
      "chi2_nfw": 22.64,
      "chi2_bec": 3.49,
      "rchi2_nfw": 0.906,
      "rchi2_bec": 0.14,
      "daic": 19.15,
      "nfw_log_rhos": 5.17,
      "nfw_log_rs": 2.5,
      "bec_log_rhoc": 7.86,
      "bec_log_rc": 0.29
    },
    {
      "name": "NGC5585",
      "logMs": 9.17,
      "xi_kpc": 1.31,
      "N_pts": 24,
      "X_min": 0.069,
      "X_med": 2.36,
      "X_max": 8.38,
      "chi2_nfw": 23.7,
      "chi2_bec": 6.48,
      "rchi2_nfw": 1.077,
      "rchi2_bec": 0.295,
      "daic": 17.21,
      "nfw_log_rhos": 5.69,
      "nfw_log_rs": 1.82,
      "bec_log_rhoc": 7.26,
      "bec_log_rc": 0.64
    },
    {
      "name": "F568-3",
      "logMs": 9.62,
      "xi_kpc": 2.2,
      "N_pts": 18,
      "X_min": 0.291,
      "X_med": 2.21,
      "X_max": 8.17,
      "chi2_nfw": 28.38,
      "chi2_bec": 11.22,
      "rchi2_nfw": 1.774,
      "rchi2_bec": 0.701,
      "daic": 17.16,
      "nfw_log_rhos": 5.66,
      "nfw_log_rs": 1.87,
      "bec_log_rhoc": 7.24,
      "bec_log_rc": 0.73
    },
    {
      "name": "NGC7331",
      "logMs": 11.1,
      "xi_kpc": 12.06,
      "N_pts": 36,
      "X_min": 0.221,
      "X_med": 1.46,
      "X_max": 3.01,
      "chi2_nfw": 46.29,
      "chi2_bec": 30.76,
      "rchi2_nfw": 1.362,
      "rchi2_bec": 0.905,
      "daic": 15.53,
      "nfw_log_rhos": 5.15,
      "nfw_log_rs": 2.5,
      "bec_log_rhoc": 6.66,
      "bec_log_rc": 1.32
    },
    {
      "name": "UGC03546",
      "logMs": 10.7,
      "xi_kpc": 7.67,
      "N_pts": 30,
      "X_min": 0.082,
      "X_med": 0.63,
      "X_max": 3.81,
      "chi2_nfw": 46.22,
      "chi2_bec": 32.71,
      "rchi2_nfw": 1.651,
      "rchi2_bec": 1.168,
      "daic": 13.51,
      "nfw_log_rhos": 5.67,
      "nfw_log_rs": 2.06,
      "bec_log_rhoc": 7.05,
      "bec_log_rc": 1.03
    },
    {
      "name": "NGC5055",
      "logMs": 10.88,
      "xi_kpc": 9.42,
      "N_pts": 28,
      "X_min": 0.076,
      "X_med": 1.67,
      "X_max": 5.79,
      "chi2_nfw": 22.43,
      "chi2_bec": 10.34,
      "rchi2_nfw": 0.863,
      "rchi2_bec": 0.398,
      "daic": 12.09,
      "nfw_log_rhos": 5.87,
      "nfw_log_rs": 1.75,
      "bec_log_rhoc": 6.6,
      "bec_log_rc": 1.25
    },
    {
      "name": "NGC6946",
      "logMs": 10.52,
      "xi_kpc": 6.2,
      "N_pts": 58,
      "X_min": 0.031,
      "X_med": 1.66,
      "X_max": 3.29,
      "chi2_nfw": 54.31,
      "chi2_bec": 42.76,
      "rchi2_nfw": 0.97,
      "rchi2_bec": 0.764,
      "daic": 11.55,
      "nfw_log_rhos": 6.27,
      "nfw_log_rs": 1.51,
      "bec_log_rhoc": 7.2,
      "bec_log_rc": 0.85
    },
    {
      "name": "NGC4088",
      "logMs": 10.73,
      "xi_kpc": 7.89,
      "N_pts": 12,
      "X_min": 0.22,
      "X_med": 1.44,
      "X_max": 2.72,
      "chi2_nfw": 18.87,
      "chi2_bec": 7.74,
      "rchi2_nfw": 1.887,
      "rchi2_bec": 0.774,
      "daic": 11.12,
      "nfw_log_rhos": 4.82,
      "nfw_log_rs": 2.5,
      "bec_log_rhoc": 6.3,
      "bec_log_rc": 1.6
    },
    {
      "name": "UGC06818",
      "logMs": 8.9,
      "xi_kpc": 0.96,
      "N_pts": 8,
      "X_min": 0.906,
      "X_med": 4.1,
      "X_max": 7.27,
      "chi2_nfw": 19.28,
      "chi2_bec": 8.34,
      "rchi2_nfw": 3.213,
      "rchi2_bec": 1.39,
      "daic": 10.94,
      "nfw_log_rhos": 4.8,
      "nfw_log_rs": 2.5,
      "bec_log_rhoc": 7.02,
      "bec_log_rc": 0.68
    },
    {
      "name": "NGC0055",
      "logMs": 9.36,
      "xi_kpc": 1.64,
      "N_pts": 21,
      "X_min": 0.75,
      "X_med": 4.5,
      "X_max": 8.23,
      "chi2_nfw": 10.34,
      "chi2_bec": 0.74,
      "rchi2_nfw": 0.544,
      "rchi2_bec": 0.039,
      "daic": 9.6,
      "nfw_log_rhos": 5.4,
      "nfw_log_rs": 1.91,
      "bec_log_rhoc": 6.91,
      "bec_log_rc": 0.76
    },
    {
      "name": "F583-1",
      "logMs": 8.69,
      "xi_kpc": 0.76,
      "N_pts": 25,
      "X_min": 0.344,
      "X_med": 5.1,
      "X_max": 21.49,
      "chi2_nfw": 23.41,
      "chi2_bec": 14.9,
      "rchi2_nfw": 1.018,
      "rchi2_bec": 0.648,
      "daic": 8.51,
      "nfw_log_rhos": 6.13,
      "nfw_log_rs": 1.38,
      "bec_log_rhoc": 7.3,
      "bec_log_rc": 0.58
    },
    {
      "name": "NGC5033",
      "logMs": 10.74,
      "xi_kpc": 8.01,
      "N_pts": 22,
      "X_min": 0.095,
      "X_med": 2.56,
      "X_max": 5.57,
      "chi2_nfw": 32.73,
      "chi2_bec": 24.32,
      "rchi2_nfw": 1.636,
      "rchi2_bec": 1.216,
      "daic": 8.41,
      "nfw_log_rhos": 6.91,
      "nfw_log_rs": 1.25,
      "bec_log_rhoc": 7.18,
      "bec_log_rc": 1.05
    },
    {
      "name": "F574-1",
      "logMs": 9.51,
      "xi_kpc": 1.95,
      "N_pts": 14,
      "X_min": 0.241,
      "X_med": 3.38,
      "X_max": 6.47,
      "chi2_nfw": 15.7,
      "chi2_bec": 7.53,
      "rchi2_nfw": 1.308,
      "rchi2_bec": 0.627,
      "daic": 8.17,
      "nfw_log_rhos": 6.58,
      "nfw_log_rs": 1.18,
      "bec_log_rhoc": 7.42,
      "bec_log_rc": 0.61
    },
    {
      "name": "UGC05750",
      "logMs": 9.22,
      "xi_kpc": 1.39,
      "N_pts": 11,
      "X_min": 0.223,
      "X_med": 3.46,
      "X_max": 16.42,
      "chi2_nfw": 8.14,
      "chi2_bec": 0.53,
      "rchi2_nfw": 0.904,
      "rchi2_bec": 0.058,
      "daic": 7.61,
      "nfw_log_rhos": 5.37,
      "nfw_log_rs": 1.81,
      "bec_log_rhoc": 6.74,
      "bec_log_rc": 0.84
    },
    {
      "name": "NGC2955",
      "logMs": 11.2,
      "xi_kpc": 13.62,
      "N_pts": 24,
      "X_min": 0.055,
      "X_med": 0.66,
      "X_max": 2.6,
      "chi2_nfw": 31.13,
      "chi2_bec": 24.63,
      "rchi2_nfw": 1.415,
      "rchi2_bec": 1.119,
      "daic": 6.5,
      "nfw_log_rhos": 6.21,
      "nfw_log_rs": 1.65,
      "bec_log_rhoc": 7.03,
      "bec_log_rc": 1.09
    },
    {
      "name": "UGC06614",
      "logMs": 10.79,
      "xi_kpc": 8.5,
      "N_pts": 13,
      "X_min": 0.38,
      "X_med": 1.85,
      "X_max": 7.6,
      "chi2_nfw": 7.85,
      "chi2_bec": 1.38,
      "rchi2_nfw": 0.714,
      "rchi2_bec": 0.125,
      "daic": 6.48,
      "nfw_log_rhos": 4.96,
      "nfw_log_rs": 2.5,
      "bec_log_rhoc": 6.45,
      "bec_log_rc": 1.4
    },
    {
      "name": "DDO168",
      "logMs": 7.98,
      "xi_kpc": 0.33,
      "N_pts": 10,
      "X_min": 1.231,
      "X_med": 6.8,
      "X_max": 12.37,
      "chi2_nfw": 7.72,
      "chi2_bec": 3.16,
      "rchi2_nfw": 0.965,
      "rchi2_bec": 0.395,
      "daic": 4.56,
      "nfw_log_rhos": 4.85,
      "nfw_log_rs": 2.5,
      "bec_log_rhoc": 7.46,
      "bec_log_rc": 0.3
    },
    {
      "name": "NGC3893",
      "logMs": 10.47,
      "xi_kpc": 5.83,
      "N_pts": 10,
      "X_min": 0.298,
      "X_med": 1.69,
      "X_max": 3.27,
      "chi2_nfw": 6.92,
      "chi2_bec": 2.46,
      "rchi2_nfw": 0.865,
      "rchi2_bec": 0.307,
      "daic": 4.47,
      "nfw_log_rhos": 6.78,
      "nfw_log_rs": 1.28,
      "bec_log_rhoc": 7.5,
      "bec_log_rc": 0.79
    },
    {
      "name": "UGC11557",
      "logMs": 9.78,
      "xi_kpc": 2.65,
      "N_pts": 12,
      "X_min": 0.124,
      "X_med": 1.6,
      "X_max": 3.98,
      "chi2_nfw": 14.84,
      "chi2_bec": 10.73,
      "rchi2_nfw": 1.484,
      "rchi2_bec": 1.073,
      "daic": 4.12,
      "nfw_log_rhos": 4.33,
      "nfw_log_rs": 2.5,
      "bec_log_rhoc": 6.25,
      "bec_log_rc": 1.12
    },
    {
      "name": "NGC5005",
      "logMs": 10.95,
      "xi_kpc": 10.19,
      "N_pts": 18,
      "X_min": 0.048,
      "X_med": 0.46,
      "X_max": 1.13,
      "chi2_nfw": 10.45,
      "chi2_bec": 6.5,
      "rchi2_nfw": 0.653,
      "rchi2_bec": 0.406,
      "daic": 3.95,
      "nfw_log_rhos": 5.41,
      "nfw_log_rs": 2.5,
      "bec_log_rhoc": 7.33,
      "bec_log_rc": 0.99
    },
    {
      "name": "UGC08837",
      "logMs": 8.4,
      "xi_kpc": 0.54,
      "N_pts": 8,
      "X_min": 0.964,
      "X_med": 4.38,
      "X_max": 7.79,
      "chi2_nfw": 6.18,
      "chi2_bec": 2.47,
      "rchi2_nfw": 1.03,
      "rchi2_bec": 0.412,
      "daic": 3.71,
      "nfw_log_rhos": 4.5,
      "nfw_log_rs": 2.5,
      "bec_log_rhoc": 6.97,
      "bec_log_rc": 0.43
    },
    {
      "name": "UGC07603",
      "logMs": 8.27,
      "xi_kpc": 0.47,
      "N_pts": 12,
      "X_min": 0.728,
      "X_med": 4.75,
      "X_max": 8.8,
      "chi2_nfw": 5.06,
      "chi2_bec": 1.41,
      "rchi2_nfw": 0.506,
      "rchi2_bec": 0.141,
      "daic": 3.65,
      "nfw_log_rhos": 6.77,
      "nfw_log_rs": 0.98,
      "bec_log_rhoc": 7.87,
      "bec_log_rc": 0.2
    },
    {
      "name": "UGC05764",
      "logMs": 7.63,
      "xi_kpc": 0.22,
      "N_pts": 10,
      "X_min": 1.62,
      "X_med": 8.96,
      "X_max": 16.29,
      "chi2_nfw": 4.71,
      "chi2_bec": 1.44,
      "rchi2_nfw": 0.589,
      "rchi2_bec": 0.18,
      "daic": 3.27,
      "nfw_log_rhos": 7.43,
      "nfw_log_rs": 0.46,
      "bec_log_rhoc": 8.06,
      "bec_log_rc": 0.04
    },
    {
      "name": "KK98-251",
      "logMs": 7.63,
      "xi_kpc": 0.22,
      "N_pts": 15,
      "X_min": 1.125,
      "X_med": 6.3,
      "X_max": 14.09,
      "chi2_nfw": 3.82,
      "chi2_bec": 0.57,
      "rchi2_nfw": 0.294,
      "rchi2_bec": 0.044,
      "daic": 3.25,
      "nfw_log_rhos": 4.43,
      "nfw_log_rs": 2.5,
      "bec_log_rhoc": 7.05,
      "bec_log_rc": 0.3
    },
    {
      "name": "UGC06399",
      "logMs": 9.06,
      "xi_kpc": 1.15,
      "N_pts": 9,
      "X_min": 0.753,
      "X_med": 3.78,
      "X_max": 6.8,
      "chi2_nfw": 4.1,
      "chi2_bec": 0.89,
      "rchi2_nfw": 0.586,
      "rchi2_bec": 0.128,
      "daic": 3.21,
      "nfw_log_rhos": 6.16,
      "nfw_log_rs": 1.48,
      "bec_log_rhoc": 7.44,
      "bec_log_rc": 0.53
    },
    {
      "name": "ESO116-G012",
      "logMs": 9.33,
      "xi_kpc": 1.58,
      "N_pts": 15,
      "X_min": 0.158,
      "X_med": 2.62,
      "X_max": 6.25,
      "chi2_nfw": 10.92,
      "chi2_bec": 7.72,
      "rchi2_nfw": 0.84,
      "rchi2_bec": 0.594,
      "daic": 3.2,
      "nfw_log_rhos": 6.43,
      "nfw_log_rs": 1.4,
      "bec_log_rhoc": 7.58,
      "bec_log_rc": 0.57
    },
    {
      "name": "DDO064",
      "logMs": 7.89,
      "xi_kpc": 0.3,
      "N_pts": 14,
      "X_min": 0.331,
      "X_med": 4.59,
      "X_max": 9.87,
      "chi2_nfw": 5.8,
      "chi2_bec": 3.1,
      "rchi2_nfw": 0.483,
      "rchi2_bec": 0.258,
      "daic": 2.71,
      "nfw_log_rhos": 4.9,
      "nfw_log_rs": 2.5,
      "bec_log_rhoc": 7.64,
      "bec_log_rc": 0.16
    },
    {
      "name": "UGC04499",
      "logMs": 8.89,
      "xi_kpc": 0.95,
      "N_pts": 9,
      "X_min": 0.958,
      "X_med": 4.79,
      "X_max": 8.62,
      "chi2_nfw": 3.92,
      "chi2_bec": 1.71,
      "rchi2_nfw": 0.56,
      "rchi2_bec": 0.244,
      "daic": 2.21,
      "nfw_log_rhos": 6.22,
      "nfw_log_rs": 1.28,
      "bec_log_rhoc": 7.31,
      "bec_log_rc": 0.5
    },
    {
      "name": "UGC04325",
      "logMs": 9.01,
      "xi_kpc": 1.08,
      "N_pts": 8,
      "X_min": 0.645,
      "X_med": 2.89,
      "X_max": 5.15,
      "chi2_nfw": 6.41,
      "chi2_bec": 4.31,
      "rchi2_nfw": 1.068,
      "rchi2_bec": 0.719,
      "daic": 2.09,
      "nfw_log_rhos": 7.56,
      "nfw_log_rs": 0.62,
      "bec_log_rhoc": 8.16,
      "bec_log_rc": 0.21
    },
    {
      "name": "UGC07323",
      "logMs": 9.31,
      "xi_kpc": 1.54,
      "N_pts": 10,
      "X_min": 0.375,
      "X_med": 2.07,
      "X_max": 3.77,
      "chi2_nfw": 3.5,
      "chi2_bec": 1.62,
      "rchi2_nfw": 0.437,
      "rchi2_bec": 0.202,
      "daic": 1.88,
      "nfw_log_rhos": 4.95,
      "nfw_log_rs": 2.5,
      "bec_log_rhoc": 7.26,
      "bec_log_rc": 0.57
    },
    {
      "name": "NGC6195",
      "logMs": 11.29,
      "xi_kpc": 15.07,
      "N_pts": 23,
      "X_min": 0.088,
      "X_med": 0.82,
      "X_max": 2.42,
      "chi2_nfw": 11.87,
      "chi2_bec": 10.28,
      "rchi2_nfw": 0.565,
      "rchi2_bec": 0.49,
      "daic": 1.58,
      "nfw_log_rhos": 5.02,
      "nfw_log_rs": 2.5,
      "bec_log_rhoc": 6.53,
      "bec_log_rc": 1.34
    },
    {
      "name": "UGC07524",
      "logMs": 9.09,
      "xi_kpc": 1.19,
      "N_pts": 31,
      "X_min": 0.294,
      "X_med": 4.63,
      "X_max": 8.99,
      "chi2_nfw": 10.07,
      "chi2_bec": 9.24,
      "rchi2_nfw": 0.347,
      "rchi2_bec": 0.319,
      "daic": 0.83,
      "nfw_log_rhos": 6.24,
      "nfw_log_rs": 1.29,
      "bec_log_rhoc": 7.24,
      "bec_log_rc": 0.58
    },
    {
      "name": "CamB",
      "logMs": 7.57,
      "xi_kpc": 0.21,
      "N_pts": 9,
      "X_min": 0.767,
      "X_med": 4.31,
      "X_max": 8.58,
      "chi2_nfw": 3.8,
      "chi2_bec": 3.11,
      "rchi2_nfw": 0.543,
      "rchi2_bec": 0.444,
      "daic": 0.69,
      "nfw_log_rhos": 4.0,
      "nfw_log_rs": 1.9,
      "bec_log_rhoc": 6.33,
      "bec_log_rc": 0.3
    },
    {
      "name": "UGC07089",
      "logMs": 9.25,
      "xi_kpc": 1.44,
      "N_pts": 12,
      "X_min": 0.603,
      "X_med": 3.93,
      "X_max": 6.35,
      "chi2_nfw": 2.25,
      "chi2_bec": 1.74,
      "rchi2_nfw": 0.225,
      "rchi2_bec": 0.174,
      "daic": 0.51,
      "nfw_log_rhos": 4.74,
      "nfw_log_rs": 2.5,
      "bec_log_rhoc": 6.9,
      "bec_log_rc": 0.73
    },
    {
      "name": "UGC04483",
      "logMs": 6.81,
      "xi_kpc": 0.09,
      "N_pts": 8,
      "X_min": 0.921,
      "X_med": 7.48,
      "X_max": 13.93,
      "chi2_nfw": 0.43,
      "chi2_bec": 0.21,
      "rchi2_nfw": 0.072,
      "rchi2_bec": 0.035,
      "daic": 0.22,
      "nfw_log_rhos": 6.08,
      "nfw_log_rs": 1.11,
      "bec_log_rhoc": 7.86,
      "bec_log_rc": -0.27
    },
    {
      "name": "NGC2915",
      "logMs": 8.51,
      "xi_kpc": 0.61,
      "N_pts": 30,
      "X_min": 0.557,
      "X_med": 8.5,
      "X_max": 16.45,
      "chi2_nfw": 26.79,
      "chi2_bec": 26.61,
      "rchi2_nfw": 0.957,
      "rchi2_bec": 0.95,
      "daic": 0.18,
      "nfw_log_rhos": 7.29,
      "nfw_log_rs": 0.73,
      "bec_log_rhoc": 7.67,
      "bec_log_rc": 0.45
    },
    {
      "name": "UGC07577",
      "logMs": 7.35,
      "xi_kpc": 0.16,
      "N_pts": 9,
      "X_min": 1.175,
      "X_med": 5.81,
      "X_max": 10.45,
      "chi2_nfw": 0.55,
      "chi2_bec": 0.42,
      "rchi2_nfw": 0.078,
      "rchi2_bec": 0.06,
      "daic": 0.13,
      "nfw_log_rhos": 4.0,
      "nfw_log_rs": 2.23,
      "bec_log_rhoc": 6.44,
      "bec_log_rc": 0.3
    },
    {
      "name": "DDO154",
      "logMs": 7.42,
      "xi_kpc": 0.18,
      "N_pts": 12,
      "X_min": 2.793,
      "X_med": 18.3,
      "X_max": 33.74,
      "chi2_nfw": 2.83,
      "chi2_bec": 2.72,
      "rchi2_nfw": 0.283,
      "rchi2_bec": 0.272,
      "daic": 0.11,
      "nfw_log_rhos": 5.94,
      "nfw_log_rs": 1.34,
      "bec_log_rhoc": 7.38,
      "bec_log_rc": 0.3
    },
    {
      "name": "NGC4157",
      "logMs": 10.72,
      "xi_kpc": 7.83,
      "N_pts": 17,
      "X_min": 0.222,
      "X_med": 2.0,
      "X_max": 3.78,
      "chi2_nfw": 5.39,
      "chi2_bec": 5.31,
      "rchi2_nfw": 0.359,
      "rchi2_bec": 0.354,
      "daic": 0.08,
      "nfw_log_rhos": 5.06,
      "nfw_log_rs": 2.5,
      "bec_log_rhoc": 6.72,
      "bec_log_rc": 1.18
    },
    {
      "name": "NGC1090",
      "logMs": 10.56,
      "xi_kpc": 6.47,
      "N_pts": 24,
      "X_min": 0.054,
      "X_med": 2.43,
      "X_max": 4.65,
      "chi2_nfw": 34.19,
      "chi2_bec": 34.16,
      "rchi2_nfw": 1.554,
      "rchi2_bec": 1.553,
      "daic": 0.03,
      "nfw_log_rhos": 6.51,
      "nfw_log_rs": 1.35,
      "bec_log_rhoc": 7.18,
      "bec_log_rc": 0.92
    },
    {
      "name": "UGC06917",
      "logMs": 9.53,
      "xi_kpc": 1.99,
      "N_pts": 11,
      "X_min": 0.874,
      "X_med": 3.07,
      "X_max": 5.26,
      "chi2_nfw": 4.16,
      "chi2_bec": 4.83,
      "rchi2_nfw": 0.462,
      "rchi2_bec": 0.537,
      "daic": -0.67,
      "nfw_log_rhos": 6.6,
      "nfw_log_rs": 1.21,
      "bec_log_rhoc": 7.48,
      "bec_log_rc": 0.59
    },
    {
      "name": "UGC05918",
      "logMs": 8.07,
      "xi_kpc": 0.37,
      "N_pts": 8,
      "X_min": 1.522,
      "X_med": 6.82,
      "X_max": 12.12,
      "chi2_nfw": 0.54,
      "chi2_bec": 1.38,
      "rchi2_nfw": 0.09,
      "rchi2_bec": 0.23,
      "daic": -0.84,
      "nfw_log_rhos": 6.55,
      "nfw_log_rs": 0.86,
      "bec_log_rhoc": 7.48,
      "bec_log_rc": 0.21
    },
    {
      "name": "NGC3972",
      "logMs": 9.86,
      "xi_kpc": 2.89,
      "N_pts": 10,
      "X_min": 0.301,
      "X_med": 1.66,
      "X_max": 3.02,
      "chi2_nfw": 8.33,
      "chi2_bec": 9.52,
      "rchi2_nfw": 1.041,
      "rchi2_bec": 1.19,
      "daic": -1.19,
      "nfw_log_rhos": 6.01,
      "nfw_log_rs": 1.81,
      "bec_log_rhoc": 7.63,
      "bec_log_rc": 0.57
    },
    {
      "name": "NGC3953",
      "logMs": 10.85,
      "xi_kpc": 9.06,
      "N_pts": 8,
      "X_min": 0.386,
      "X_med": 1.06,
      "X_max": 1.73,
      "chi2_nfw": 0.58,
      "chi2_bec": 2.15,
      "rchi2_nfw": 0.096,
      "rchi2_bec": 0.358,
      "daic": -1.57,
      "nfw_log_rhos": 7.47,
      "nfw_log_rs": 0.9,
      "bec_log_rhoc": 7.76,
      "bec_log_rc": 0.66
    },
    {
      "name": "NGC4559",
      "logMs": 9.99,
      "xi_kpc": 3.35,
      "N_pts": 32,
      "X_min": 0.2,
      "X_med": 3.22,
      "X_max": 6.25,
      "chi2_nfw": 7.55,
      "chi2_bec": 10.06,
      "rchi2_nfw": 0.252,
      "rchi2_bec": 0.335,
      "daic": -2.51,
      "nfw_log_rhos": 6.22,
      "nfw_log_rs": 1.41,
      "bec_log_rhoc": 6.96,
      "bec_log_rc": 0.89
    },
    {
      "name": "F568-V1",
      "logMs": 9.28,
      "xi_kpc": 1.49,
      "N_pts": 15,
      "X_min": 0.262,
      "X_med": 3.94,
      "X_max": 11.83,
      "chi2_nfw": 2.82,
      "chi2_bec": 5.63,
      "rchi2_nfw": 0.217,
      "rchi2_bec": 0.433,
      "daic": -2.81,
      "nfw_log_rhos": 7.24,
      "nfw_log_rs": 0.9,
      "bec_log_rhoc": 7.72,
      "bec_log_rc": 0.55
    },
    {
      "name": "UGC12632",
      "logMs": 8.81,
      "xi_kpc": 0.87,
      "N_pts": 15,
      "X_min": 0.817,
      "X_med": 6.55,
      "X_max": 12.26,
      "chi2_nfw": 2.89,
      "chi2_bec": 5.84,
      "rchi2_nfw": 0.223,
      "rchi2_bec": 0.45,
      "daic": -2.95,
      "nfw_log_rhos": 6.62,
      "nfw_log_rs": 0.99,
      "bec_log_rhoc": 7.29,
      "bec_log_rc": 0.53
    },
    {
      "name": "NGC3726",
      "logMs": 10.55,
      "xi_kpc": 6.39,
      "N_pts": 12,
      "X_min": 0.548,
      "X_med": 2.05,
      "X_max": 5.09,
      "chi2_nfw": 8.96,
      "chi2_bec": 13.07,
      "rchi2_nfw": 0.896,
      "rchi2_bec": 1.307,
      "daic": -4.11,
      "nfw_log_rhos": 4.94,
      "nfw_log_rs": 2.5,
      "bec_log_rhoc": 6.61,
      "bec_log_rc": 1.2
    },
    {
      "name": "UGC00191",
      "logMs": 9.0,
      "xi_kpc": 1.08,
      "N_pts": 9,
      "X_min": 0.575,
      "X_med": 1.5,
      "X_max": 9.25,
      "chi2_nfw": 5.76,
      "chi2_bec": 10.08,
      "rchi2_nfw": 0.823,
      "rchi2_bec": 1.44,
      "daic": -4.32,
      "nfw_log_rhos": 6.89,
      "nfw_log_rs": 0.9,
      "bec_log_rhoc": 7.82,
      "bec_log_rc": 0.35
    },
    {
      "name": "UGC05005",
      "logMs": 9.31,
      "xi_kpc": 1.54,
      "N_pts": 11,
      "X_min": 0.505,
      "X_med": 5.57,
      "X_max": 18.54,
      "chi2_nfw": 1.96,
      "chi2_bec": 6.29,
      "rchi2_nfw": 0.218,
      "rchi2_bec": 0.699,
      "daic": -4.33,
      "nfw_log_rhos": 5.19,
      "nfw_log_rs": 2.03,
      "bec_log_rhoc": 6.83,
      "bec_log_rc": 0.89
    },
    {
      "name": "UGC05829",
      "logMs": 8.45,
      "xi_kpc": 0.57,
      "N_pts": 11,
      "X_min": 1.101,
      "X_med": 6.59,
      "X_max": 12.07,
      "chi2_nfw": 0.77,
      "chi2_bec": 5.1,
      "rchi2_nfw": 0.085,
      "rchi2_bec": 0.567,
      "daic": -4.33,
      "nfw_log_rhos": 5.1,
      "nfw_log_rs": 2.16,
      "bec_log_rhoc": 7.22,
      "bec_log_rc": 0.46
    },
    {
      "name": "UGCA444",
      "logMs": 6.78,
      "xi_kpc": 0.08,
      "N_pts": 36,
      "X_min": 1.437,
      "X_med": 16.35,
      "X_max": 31.38,
      "chi2_nfw": 1.1,
      "chi2_bec": 5.6,
      "rchi2_nfw": 0.032,
      "rchi2_bec": 0.165,
      "daic": -4.5,
      "nfw_log_rhos": 4.7,
      "nfw_log_rs": 2.5,
      "bec_log_rhoc": 7.49,
      "bec_log_rc": 0.11
    },
    {
      "name": "UGC05253",
      "logMs": 10.93,
      "xi_kpc": 9.98,
      "N_pts": 73,
      "X_min": 0.013,
      "X_med": 0.47,
      "X_max": 5.34,
      "chi2_nfw": 43.16,
      "chi2_bec": 47.72,
      "rchi2_nfw": 0.608,
      "rchi2_bec": 0.672,
      "daic": -4.56,
      "nfw_log_rhos": 6.65,
      "nfw_log_rs": 1.43,
      "bec_log_rhoc": 7.24,
      "bec_log_rc": 1.07
    },
    {
      "name": "UGCA442",
      "logMs": 7.85,
      "xi_kpc": 0.29,
      "N_pts": 8,
      "X_min": 1.473,
      "X_med": 11.84,
      "X_max": 22.2,
      "chi2_nfw": 1.57,
      "chi2_bec": 7.08,
      "rchi2_nfw": 0.262,
      "rchi2_bec": 1.18,
      "daic": -5.51,
      "nfw_log_rhos": 5.76,
      "nfw_log_rs": 1.6,
      "bec_log_rhoc": 7.53,
      "bec_log_rc": 0.3
    },
    {
      "name": "NGC3769",
      "logMs": 9.97,
      "xi_kpc": 3.29,
      "N_pts": 12,
      "X_min": 0.528,
      "X_med": 3.46,
      "X_max": 11.28,
      "chi2_nfw": 9.3,
      "chi2_bec": 15.94,
      "rchi2_nfw": 0.93,
      "rchi2_bec": 1.594,
      "daic": -6.64,
      "nfw_log_rhos": 6.5,
      "nfw_log_rs": 1.26,
      "bec_log_rhoc": 6.9,
      "bec_log_rc": 0.98
    },
    {
      "name": "UGC06930",
      "logMs": 9.65,
      "xi_kpc": 2.28,
      "N_pts": 10,
      "X_min": 0.764,
      "X_med": 4.21,
      "X_max": 7.29,
      "chi2_nfw": 2.22,
      "chi2_bec": 9.18,
      "rchi2_nfw": 0.277,
      "rchi2_bec": 1.148,
      "daic": -6.96,
      "nfw_log_rhos": 6.88,
      "nfw_log_rs": 1.0,
      "bec_log_rhoc": 7.28,
      "bec_log_rc": 0.69
    },
    {
      "name": "NGC7793",
      "logMs": 9.55,
      "xi_kpc": 2.02,
      "N_pts": 46,
      "X_min": 0.054,
      "X_med": 0.82,
      "X_max": 3.89,
      "chi2_nfw": 38.17,
      "chi2_bec": 45.78,
      "rchi2_nfw": 0.868,
      "rchi2_bec": 1.04,
      "daic": -7.61,
      "nfw_log_rhos": 7.05,
      "nfw_log_rs": 0.89,
      "bec_log_rhoc": 7.83,
      "bec_log_rc": 0.37
    },
    {
      "name": "NGC0300",
      "logMs": 9.16,
      "xi_kpc": 1.3,
      "N_pts": 25,
      "X_min": 0.699,
      "X_med": 4.88,
      "X_max": 9.06,
      "chi2_nfw": 10.43,
      "chi2_bec": 18.67,
      "rchi2_nfw": 0.454,
      "rchi2_bec": 0.812,
      "daic": -8.24,
      "nfw_log_rhos": 6.48,
      "nfw_log_rs": 1.24,
      "bec_log_rhoc": 7.42,
      "bec_log_rc": 0.59
    },
    {
      "name": "F583-4",
      "logMs": 8.93,
      "xi_kpc": 1.0,
      "N_pts": 12,
      "X_min": 0.22,
      "X_med": 4.68,
      "X_max": 7.3,
      "chi2_nfw": 1.28,
      "chi2_bec": 9.7,
      "rchi2_nfw": 0.128,
      "rchi2_bec": 0.97,
      "daic": -8.42,
      "nfw_log_rhos": 5.95,
      "nfw_log_rs": 1.46,
      "bec_log_rhoc": 7.23,
      "bec_log_rc": 0.5
    },
    {
      "name": "NGC2683",
      "logMs": 10.6,
      "xi_kpc": 6.83,
      "N_pts": 11,
      "X_min": 0.423,
      "X_med": 2.53,
      "X_max": 5.07,
      "chi2_nfw": 6.13,
      "chi2_bec": 15.4,
      "rchi2_nfw": 0.681,
      "rchi2_bec": 1.711,
      "daic": -9.28,
      "nfw_log_rhos": 7.5,
      "nfw_log_rs": 0.86,
      "bec_log_rhoc": 7.4,
      "bec_log_rc": 0.85
    },
    {
      "name": "NGC4100",
      "logMs": 10.47,
      "xi_kpc": 5.87,
      "N_pts": 24,
      "X_min": 0.444,
      "X_med": 2.15,
      "X_max": 3.88,
      "chi2_nfw": 10.15,
      "chi2_bec": 19.95,
      "rchi2_nfw": 0.461,
      "rchi2_bec": 0.907,
      "daic": -9.8,
      "nfw_log_rhos": 7.52,
      "nfw_log_rs": 0.85,
      "bec_log_rhoc": 7.64,
      "bec_log_rc": 0.74
    },
    {
      "name": "UGC06983",
      "logMs": 9.42,
      "xi_kpc": 1.75,
      "N_pts": 17,
      "X_min": 0.992,
      "X_med": 4.97,
      "X_max": 8.94,
      "chi2_nfw": 8.55,
      "chi2_bec": 19.55,
      "rchi2_nfw": 0.57,
      "rchi2_bec": 1.303,
      "daic": -11.0,
      "nfw_log_rhos": 7.09,
      "nfw_log_rs": 0.92,
      "bec_log_rhoc": 7.51,
      "bec_log_rc": 0.61
    },
    {
      "name": "NGC3992",
      "logMs": 11.05,
      "xi_kpc": 11.48,
      "N_pts": 9,
      "X_min": 0.8,
      "X_med": 2.4,
      "X_max": 4.01,
      "chi2_nfw": 0.96,
      "chi2_bec": 12.41,
      "rchi2_nfw": 0.137,
      "rchi2_bec": 1.773,
      "daic": -11.45,
      "nfw_log_rhos": 7.45,
      "nfw_log_rs": 1.06,
      "bec_log_rhoc": 7.35,
      "bec_log_rc": 1.05
    },
    {
      "name": "UGC05721",
      "logMs": 8.42,
      "xi_kpc": 0.56,
      "N_pts": 23,
      "X_min": 0.162,
      "X_med": 3.73,
      "X_max": 12.14,
      "chi2_nfw": 17.23,
      "chi2_bec": 28.83,
      "rchi2_nfw": 0.82,
      "rchi2_bec": 1.373,
      "daic": -11.61,
      "nfw_log_rhos": 7.88,
      "nfw_log_rs": 0.4,
      "bec_log_rhoc": 8.25,
      "bec_log_rc": 0.16
    },
    {
      "name": "DDO170",
      "logMs": 8.43,
      "xi_kpc": 0.56,
      "N_pts": 8,
      "X_min": 3.33,
      "X_med": 12.64,
      "X_max": 21.96,
      "chi2_nfw": 1.67,
      "chi2_bec": 16.54,
      "rchi2_nfw": 0.279,
      "rchi2_bec": 2.757,
      "daic": -14.87,
      "nfw_log_rhos": 5.96,
      "nfw_log_rs": 1.3,
      "bec_log_rhoc": 7.27,
      "bec_log_rc": 0.45
    },
    {
      "name": "NGC0801",
      "logMs": 11.19,
      "xi_kpc": 13.47,
      "N_pts": 13,
      "X_min": 0.087,
      "X_med": 1.31,
      "X_max": 4.44,
      "chi2_nfw": 31.31,
      "chi2_bec": 47.41,
      "rchi2_nfw": 2.847,
      "rchi2_bec": 4.31,
      "daic": -16.1,
      "nfw_log_rhos": 6.37,
      "nfw_log_rs": 1.5,
      "bec_log_rhoc": 6.56,
      "bec_log_rc": 1.31
    },
    {
      "name": "UGC07399",
      "logMs": 8.76,
      "xi_kpc": 0.82,
      "N_pts": 10,
      "X_min": 0.744,
      "X_med": 4.12,
      "X_max": 7.48,
      "chi2_nfw": 2.41,
      "chi2_bec": 20.8,
      "rchi2_nfw": 0.302,
      "rchi2_bec": 2.6,
      "daic": -18.39,
      "nfw_log_rhos": 7.42,
      "nfw_log_rs": 0.77,
      "bec_log_rhoc": 8.11,
      "bec_log_rc": 0.3
    },
    {
      "name": "NGC3521",
      "logMs": 10.63,
      "xi_kpc": 7.02,
      "N_pts": 41,
      "X_min": 0.073,
      "X_med": 0.56,
      "X_max": 2.53,
      "chi2_nfw": 8.26,
      "chi2_bec": 26.69,
      "rchi2_nfw": 0.212,
      "rchi2_bec": 0.684,
      "daic": -18.43,
      "nfw_log_rhos": 6.59,
      "nfw_log_rs": 1.48,
      "bec_log_rhoc": 7.55,
      "bec_log_rc": 0.81
    },
    {
      "name": "UGC02259",
      "logMs": 8.94,
      "xi_kpc": 1.0,
      "N_pts": 8,
      "X_min": 1.019,
      "X_med": 4.58,
      "X_max": 8.13,
      "chi2_nfw": 0.64,
      "chi2_bec": 21.05,
      "rchi2_nfw": 0.106,
      "rchi2_bec": 3.508,
      "daic": -20.41,
      "nfw_log_rhos": 7.53,
      "nfw_log_rs": 0.61,
      "bec_log_rhoc": 7.9,
      "bec_log_rc": 0.34
    },
    {
      "name": "IC2574",
      "logMs": 8.71,
      "xi_kpc": 0.77,
      "N_pts": 34,
      "X_min": 1.107,
      "X_med": 7.22,
      "X_max": 13.32,
      "chi2_nfw": 19.03,
      "chi2_bec": 40.02,
      "rchi2_nfw": 0.595,
      "rchi2_bec": 1.251,
      "daic": -20.99,
      "nfw_log_rhos": 4.54,
      "nfw_log_rs": 2.5,
      "bec_log_rhoc": 6.88,
      "bec_log_rc": 0.58
    },
    {
      "name": "NGC3741",
      "logMs": 7.15,
      "xi_kpc": 0.13,
      "N_pts": 21,
      "X_min": 1.804,
      "X_med": 20.15,
      "X_max": 54.89,
      "chi2_nfw": 1.35,
      "chi2_bec": 22.96,
      "rchi2_nfw": 0.071,
      "rchi2_bec": 1.209,
      "daic": -21.61,
      "nfw_log_rhos": 5.91,
      "nfw_log_rs": 1.37,
      "bec_log_rhoc": 7.41,
      "bec_log_rc": 0.3
    },
    {
      "name": "UGC06446",
      "logMs": 8.69,
      "xi_kpc": 0.76,
      "N_pts": 17,
      "X_min": 0.766,
      "X_med": 6.9,
      "X_max": 13.49,
      "chi2_nfw": 2.74,
      "chi2_bec": 24.45,
      "rchi2_nfw": 0.183,
      "rchi2_bec": 1.63,
      "daic": -21.71,
      "nfw_log_rhos": 7.23,
      "nfw_log_rs": 0.73,
      "bec_log_rhoc": 7.66,
      "bec_log_rc": 0.42
    },
    {
      "name": "UGC05716",
      "logMs": 8.47,
      "xi_kpc": 0.58,
      "N_pts": 12,
      "X_min": 1.763,
      "X_med": 11.49,
      "X_max": 21.17,
      "chi2_nfw": 0.68,
      "chi2_bec": 26.41,
      "rchi2_nfw": 0.068,
      "rchi2_bec": 2.641,
      "daic": -25.73,
      "nfw_log_rhos": 6.77,
      "nfw_log_rs": 0.92,
      "bec_log_rhoc": 7.47,
      "bec_log_rc": 0.47
    },
    {
      "name": "NGC0024",
      "logMs": 9.29,
      "xi_kpc": 1.5,
      "N_pts": 29,
      "X_min": 0.14,
      "X_med": 1.13,
      "X_max": 7.5,
      "chi2_nfw": 20.51,
      "chi2_bec": 52.69,
      "rchi2_nfw": 0.759,
      "rchi2_bec": 1.951,
      "daic": -32.18,
      "nfw_log_rhos": 7.67,
      "nfw_log_rs": 0.64,
      "bec_log_rhoc": 8.23,
      "bec_log_rc": 0.33
    },
    {
      "name": "UGC12732",
      "logMs": 8.92,
      "xi_kpc": 0.98,
      "N_pts": 16,
      "X_min": 0.976,
      "X_med": 8.29,
      "X_max": 15.65,
      "chi2_nfw": 1.42,
      "chi2_bec": 33.83,
      "rchi2_nfw": 0.101,
      "rchi2_bec": 2.416,
      "daic": -32.41,
      "nfw_log_rhos": 6.53,
      "nfw_log_rs": 1.14,
      "bec_log_rhoc": 7.17,
      "bec_log_rc": 0.69
    },
    {
      "name": "UGC00731",
      "logMs": 8.21,
      "xi_kpc": 0.43,
      "N_pts": 12,
      "X_min": 2.101,
      "X_med": 13.63,
      "X_max": 25.19,
      "chi2_nfw": 0.92,
      "chi2_bec": 33.35,
      "rchi2_nfw": 0.092,
      "rchi2_bec": 3.335,
      "daic": -32.42,
      "nfw_log_rhos": 6.8,
      "nfw_log_rs": 0.89,
      "bec_log_rhoc": 7.7,
      "bec_log_rc": 0.34
    },
    {
      "name": "UGC02885",
      "logMs": 11.3,
      "xi_kpc": 15.31,
      "N_pts": 19,
      "X_min": 0.111,
      "X_med": 2.55,
      "X_max": 4.84,
      "chi2_nfw": 19.49,
      "chi2_bec": 55.05,
      "rchi2_nfw": 1.147,
      "rchi2_bec": 3.238,
      "daic": -35.56,
      "nfw_log_rhos": 6.47,
      "nfw_log_rs": 1.64,
      "bec_log_rhoc": 6.73,
      "bec_log_rc": 1.4
    },
    {
      "name": "UGC08699",
      "logMs": 10.4,
      "xi_kpc": 5.41,
      "N_pts": 41,
      "X_min": 0.041,
      "X_med": 1.32,
      "X_max": 4.75,
      "chi2_nfw": 19.2,
      "chi2_bec": 57.98,
      "rchi2_nfw": 0.492,
      "rchi2_bec": 1.487,
      "daic": -38.78,
      "nfw_log_rhos": 7.03,
      "nfw_log_rs": 1.15,
      "bec_log_rhoc": 7.42,
      "bec_log_rc": 0.86
    },
    {
      "name": "NGC0289",
      "logMs": 10.56,
      "xi_kpc": 6.47,
      "N_pts": 28,
      "X_min": 0.232,
      "X_med": 4.68,
      "X_max": 10.99,
      "chi2_nfw": 19.4,
      "chi2_bec": 58.25,
      "rchi2_nfw": 0.746,
      "rchi2_bec": 2.24,
      "daic": -38.85,
      "nfw_log_rhos": 6.61,
      "nfw_log_rs": 1.33,
      "bec_log_rhoc": 6.59,
      "bec_log_rc": 1.27
    },
    {
      "name": "UGC11820",
      "logMs": 8.69,
      "xi_kpc": 0.75,
      "N_pts": 10,
      "X_min": 0.346,
      "X_med": 4.18,
      "X_max": 21.08,
      "chi2_nfw": 4.15,
      "chi2_bec": 44.94,
      "rchi2_nfw": 0.519,
      "rchi2_bec": 5.618,
      "daic": -40.79,
      "nfw_log_rhos": 6.37,
      "nfw_log_rs": 1.16,
      "bec_log_rhoc": 7.29,
      "bec_log_rc": 0.57
    },
    {
      "name": "NGC4183",
      "logMs": 9.73,
      "xi_kpc": 2.51,
      "N_pts": 23,
      "X_min": 0.347,
      "X_med": 4.17,
      "X_max": 8.38,
      "chi2_nfw": 3.32,
      "chi2_bec": 44.94,
      "rchi2_nfw": 0.158,
      "rchi2_bec": 2.14,
      "daic": -41.62,
      "nfw_log_rhos": 7.03,
      "nfw_log_rs": 0.93,
      "bec_log_rhoc": 7.35,
      "bec_log_rc": 0.69
    },
    {
      "name": "D631-7",
      "logMs": 7.99,
      "xi_kpc": 0.34,
      "N_pts": 16,
      "X_min": 1.334,
      "X_med": 11.31,
      "X_max": 21.31,
      "chi2_nfw": 14.15,
      "chi2_bec": 56.85,
      "rchi2_nfw": 1.011,
      "rchi2_bec": 4.061,
      "daic": -42.7,
      "nfw_log_rhos": 4.71,
      "nfw_log_rs": 2.5,
      "bec_log_rhoc": 7.46,
      "bec_log_rc": 0.3
    },
    {
      "name": "NGC6503",
      "logMs": 9.81,
      "xi_kpc": 2.73,
      "N_pts": 31,
      "X_min": 0.278,
      "X_med": 4.44,
      "X_max": 8.6,
      "chi2_nfw": 8.38,
      "chi2_bec": 53.67,
      "rchi2_nfw": 0.289,
      "rchi2_bec": 1.851,
      "daic": -45.28,
      "nfw_log_rhos": 6.94,
      "nfw_log_rs": 1.02,
      "bec_log_rhoc": 7.18,
      "bec_log_rc": 0.81
    },
    {
      "name": "NGC0247",
      "logMs": 9.56,
      "xi_kpc": 2.06,
      "N_pts": 26,
      "X_min": 0.523,
      "X_med": 3.78,
      "X_max": 7.05,
      "chi2_nfw": 5.73,
      "chi2_bec": 51.76,
      "rchi2_nfw": 0.239,
      "rchi2_bec": 2.157,
      "daic": -46.03,
      "nfw_log_rhos": 6.27,
      "nfw_log_rs": 1.37,
      "bec_log_rhoc": 7.21,
      "bec_log_rc": 0.69
    },
    {
      "name": "NGC3109",
      "logMs": 7.99,
      "xi_kpc": 0.34,
      "N_pts": 25,
      "X_min": 0.775,
      "X_med": 9.98,
      "X_max": 19.22,
      "chi2_nfw": 14.07,
      "chi2_bec": 60.46,
      "rchi2_nfw": 0.612,
      "rchi2_bec": 2.629,
      "daic": -46.4,
      "nfw_log_rhos": 4.88,
      "nfw_log_rs": 2.5,
      "bec_log_rhoc": 7.58,
      "bec_log_rc": 0.3
    },
    {
      "name": "UGC02487",
      "logMs": 11.39,
      "xi_kpc": 16.87,
      "N_pts": 17,
      "X_min": 0.589,
      "X_med": 2.38,
      "X_max": 4.76,
      "chi2_nfw": 4.31,
      "chi2_bec": 54.88,
      "rchi2_nfw": 0.287,
      "rchi2_bec": 3.658,
      "daic": -50.57,
      "nfw_log_rhos": 7.53,
      "nfw_log_rs": 1.19,
      "bec_log_rhoc": 7.44,
      "bec_log_rc": 1.19
    },
    {
      "name": "NGC2998",
      "logMs": 10.88,
      "xi_kpc": 9.36,
      "N_pts": 13,
      "X_min": 0.035,
      "X_med": 1.34,
      "X_max": 4.52,
      "chi2_nfw": 13.76,
      "chi2_bec": 69.36,
      "rchi2_nfw": 1.251,
      "rchi2_bec": 6.306,
      "daic": -55.61,
      "nfw_log_rhos": 7.52,
      "nfw_log_rs": 0.94,
      "bec_log_rhoc": 7.11,
      "bec_log_rc": 1.07
    },
    {
      "name": "UGC06787",
      "logMs": 10.69,
      "xi_kpc": 7.55,
      "N_pts": 71,
      "X_min": 0.016,
      "X_med": 0.86,
      "X_max": 4.92,
      "chi2_nfw": 98.39,
      "chi2_bec": 156.44,
      "rchi2_nfw": 1.426,
      "rchi2_bec": 2.267,
      "daic": -58.05,
      "nfw_log_rhos": 6.63,
      "nfw_log_rs": 1.54,
      "bec_log_rhoc": 7.45,
      "bec_log_rc": 0.99
    },
    {
      "name": "NGC5371",
      "logMs": 11.23,
      "xi_kpc": 14.06,
      "N_pts": 19,
      "X_min": 0.103,
      "X_med": 1.44,
      "X_max": 3.29,
      "chi2_nfw": 26.84,
      "chi2_bec": 84.95,
      "rchi2_nfw": 1.579,
      "rchi2_bec": 4.997,
      "daic": -58.11,
      "nfw_log_rhos": 7.65,
      "nfw_log_rs": 0.8,
      "bec_log_rhoc": 7.32,
      "bec_log_rc": 0.91
    },
    {
      "name": "UGC11914",
      "logMs": 10.88,
      "xi_kpc": 9.33,
      "N_pts": 65,
      "X_min": 0.03,
      "X_med": 0.41,
      "X_max": 1.05,
      "chi2_nfw": 20.47,
      "chi2_bec": 79.71,
      "rchi2_nfw": 0.325,
      "rchi2_bec": 1.265,
      "daic": -59.24,
      "nfw_log_rhos": 8.53,
      "nfw_log_rs": 0.45,
      "bec_log_rhoc": 8.74,
      "bec_log_rc": 0.27
    },
    {
      "name": "NGC5985",
      "logMs": 11.02,
      "xi_kpc": 11.01,
      "N_pts": 33,
      "X_min": 0.322,
      "X_med": 1.42,
      "X_max": 3.15,
      "chi2_nfw": 10.01,
      "chi2_bec": 73.12,
      "rchi2_nfw": 0.323,
      "rchi2_bec": 2.359,
      "daic": -63.11,
      "nfw_log_rhos": 7.91,
      "nfw_log_rs": 0.91,
      "bec_log_rhoc": 8.04,
      "bec_log_rc": 0.79
    },
    {
      "name": "UGC08490",
      "logMs": 8.71,
      "xi_kpc": 0.77,
      "N_pts": 30,
      "X_min": 0.442,
      "X_med": 6.82,
      "X_max": 13.21,
      "chi2_nfw": 1.71,
      "chi2_bec": 68.18,
      "rchi2_nfw": 0.061,
      "rchi2_bec": 2.435,
      "daic": -66.46,
      "nfw_log_rhos": 7.66,
      "nfw_log_rs": 0.5,
      "bec_log_rhoc": 7.81,
      "bec_log_rc": 0.36
    },
    {
      "name": "NGC6674",
      "logMs": 11.03,
      "xi_kpc": 11.17,
      "N_pts": 15,
      "X_min": 0.224,
      "X_med": 3.36,
      "X_max": 6.49,
      "chi2_nfw": 13.36,
      "chi2_bec": 81.95,
      "rchi2_nfw": 1.028,
      "rchi2_bec": 6.304,
      "daic": -68.59,
      "nfw_log_rhos": 7.53,
      "nfw_log_rs": 1.05,
      "bec_log_rhoc": 7.18,
      "bec_log_rc": 1.16
    },
    {
      "name": "UGC06786",
      "logMs": 10.56,
      "xi_kpc": 6.53,
      "N_pts": 45,
      "X_min": 0.025,
      "X_med": 0.92,
      "X_max": 5.21,
      "chi2_nfw": 10.88,
      "chi2_bec": 85.13,
      "rchi2_nfw": 0.253,
      "rchi2_bec": 1.98,
      "daic": -74.25,
      "nfw_log_rhos": 7.19,
      "nfw_log_rs": 1.18,
      "bec_log_rhoc": 7.65,
      "bec_log_rc": 0.88
    },
    {
      "name": "NGC1003",
      "logMs": 9.53,
      "xi_kpc": 1.99,
      "N_pts": 36,
      "X_min": 0.628,
      "X_med": 7.91,
      "X_max": 15.19,
      "chi2_nfw": 17.42,
      "chi2_bec": 93.16,
      "rchi2_nfw": 0.512,
      "rchi2_bec": 2.74,
      "daic": -75.74,
      "nfw_log_rhos": 6.13,
      "nfw_log_rs": 1.45,
      "bec_log_rhoc": 6.76,
      "bec_log_rc": 1.0
    },
    {
      "name": "NGC3198",
      "logMs": 10.28,
      "xi_kpc": 4.72,
      "N_pts": 43,
      "X_min": 0.068,
      "X_med": 1.5,
      "X_max": 9.35,
      "chi2_nfw": 17.62,
      "chi2_bec": 108.99,
      "rchi2_nfw": 0.43,
      "rchi2_bec": 2.658,
      "daic": -91.37,
      "nfw_log_rhos": 6.66,
      "nfw_log_rs": 1.26,
      "bec_log_rhoc": 7.23,
      "bec_log_rc": 0.93
    },
    {
      "name": "UGC00128",
      "logMs": 9.78,
      "xi_kpc": 2.64,
      "N_pts": 22,
      "X_min": 0.473,
      "X_med": 10.42,
      "X_max": 20.34,
      "chi2_nfw": 4.23,
      "chi2_bec": 100.67,
      "rchi2_nfw": 0.211,
      "rchi2_bec": 5.034,
      "daic": -96.45,
      "nfw_log_rhos": 6.57,
      "nfw_log_rs": 1.26,
      "bec_log_rhoc": 6.81,
      "bec_log_rc": 1.08
    },
    {
      "name": "DDO161",
      "logMs": 8.44,
      "xi_kpc": 0.56,
      "N_pts": 31,
      "X_min": 1.064,
      "X_med": 11.13,
      "X_max": 23.7,
      "chi2_nfw": 6.34,
      "chi2_bec": 126.66,
      "rchi2_nfw": 0.219,
      "rchi2_bec": 4.368,
      "daic": -120.32,
      "nfw_log_rhos": 4.55,
      "nfw_log_rs": 2.5,
      "bec_log_rhoc": 7.24,
      "bec_log_rc": 0.45
    },
    {
      "name": "UGC09133",
      "logMs": 11.15,
      "xi_kpc": 12.82,
      "N_pts": 68,
      "X_min": 0.025,
      "X_med": 0.98,
      "X_max": 8.45,
      "chi2_nfw": 39.11,
      "chi2_bec": 174.74,
      "rchi2_nfw": 0.593,
      "rchi2_bec": 2.648,
      "daic": -135.63,
      "nfw_log_rhos": 6.74,
      "nfw_log_rs": 1.41,
      "bec_log_rhoc": 6.9,
      "bec_log_rc": 1.28
    },
    {
      "name": "UGC03205",
      "logMs": 10.75,
      "xi_kpc": 8.12,
      "N_pts": 48,
      "X_min": 0.034,
      "X_med": 1.0,
      "X_max": 4.93,
      "chi2_nfw": 50.18,
      "chi2_bec": 204.02,
      "rchi2_nfw": 1.091,
      "rchi2_bec": 4.435,
      "daic": -153.84,
      "nfw_log_rhos": 7.47,
      "nfw_log_rs": 0.98,
      "bec_log_rhoc": 7.74,
      "bec_log_rc": 0.78
    },
    {
      "name": "UGC02953",
      "logMs": 11.11,
      "xi_kpc": 12.28,
      "N_pts": 115,
      "X_min": 0.007,
      "X_med": 0.53,
      "X_max": 5.08,
      "chi2_nfw": 120.66,
      "chi2_bec": 292.01,
      "rchi2_nfw": 1.068,
      "rchi2_bec": 2.584,
      "daic": -171.34,
      "nfw_log_rhos": 7.04,
      "nfw_log_rs": 1.32,
      "bec_log_rhoc": 7.55,
      "bec_log_rc": 1.03
    },
    {
      "name": "NGC2841",
      "logMs": 10.97,
      "xi_kpc": 10.45,
      "N_pts": 50,
      "X_min": 0.329,
      "X_med": 1.28,
      "X_max": 6.09,
      "chi2_nfw": 19.69,
      "chi2_bec": 258.76,
      "rchi2_nfw": 0.41,
      "rchi2_bec": 5.391,
      "daic": -239.07,
      "nfw_log_rhos": 7.64,
      "nfw_log_rs": 1.07,
      "bec_log_rhoc": 7.73,
      "bec_log_rc": 0.99
    },
    {
      "name": "NGC2403",
      "logMs": 9.7,
      "xi_kpc": 2.41,
      "N_pts": 73,
      "X_min": 0.066,
      "X_med": 1.57,
      "X_max": 8.64,
      "chi2_nfw": 29.96,
      "chi2_bec": 277.01,
      "rchi2_nfw": 0.422,
      "rchi2_bec": 3.902,
      "daic": -247.05,
      "nfw_log_rhos": 6.77,
      "nfw_log_rs": 1.19,
      "bec_log_rhoc": 7.51,
      "bec_log_rc": 0.71
    },
    {
      "name": "NGC6015",
      "logMs": 10.21,
      "xi_kpc": 4.32,
      "N_pts": 44,
      "X_min": 0.079,
      "X_med": 2.67,
      "X_max": 6.77,
      "chi2_nfw": 50.78,
      "chi2_bec": 368.85,
      "rchi2_nfw": 1.209,
      "rchi2_bec": 8.782,
      "daic": -318.07,
      "nfw_log_rhos": 7.23,
      "nfw_log_rs": 0.99,
      "bec_log_rhoc": 7.6,
      "bec_log_rc": 0.75
    }
  ]
}